{
    "user_id": "f663cf48-8526-43fa-8111-20c698676665",
    "name": "Chelsea Peterson",
    "email": "browndean@example.com",
    "instagram_handle": "@judy73",
    "tiktok_handle": "@annejohnson",
    "joined_at": "2024-01-26T08:16:42.699097",
    "advocacy_programs": [
        {
            "program_id": "3f2be18b-7bb4-4378-95a5-757ff72ffec3",
            "brand": "Flores, Shaw and Murphy",
            "tasks_completed": [
                {
                    "task_id": "20336747-c716-4203-9c7d-e39e95190382",
                    "platform": "Twitter",
                    "post_url": "https://walker.org/",
                    "likes": 483,
                    "comments": 29,
                    "shares": 21,
                    "reach": -1000
                }
            ],
            "total_sales_attributed": 1711.96
        }
    ]
}