{
    "user_id": "a70c272a-53d8-499e-b3c8-d728f52051a3",
    "name": "Julia Zamora",
    "email": "griffindenise@example.net",
    "instagram_handle": "@carolynwalker",
    "tiktok_handle": "@jameshendricks",
    "joined_at": "2025-03-29T13:26:07.711486",
    "advocacy_programs": [
        {
            "program_id": "d47e5a1a-8529-41a5-9d98-0940c21a3977",
            "brand": "Phillips Inc",
            "tasks_completed": [
                {
                    "task_id": "7a44ea73-ee77-4da1-95dd-39a11d91c88e",
                    "platform": "TikTok",
                    "post_url": "http://henderson.com/",
                    "likes": 3273,
                    "comments": 93,
                    "shares": 44,
                    "reach": 570
                }
            ],
            "total_sales_attributed": 3189.56
        }
    ]
}