{
    "user_id": "0e22f39d-8351-43df-9af9-1005181818b8",
    "name": "Mercedes Allen",
    "email": "emily59@example.org",
    "instagram_handle": "@lbell",
    "tiktok_handle": "@brownsherry",
    "joined_at": "2024-12-30T04:08:17.503699",
    "advocacy_programs": [
        {
            "program_id": "c26f6d79-5ecc-4f6c-b262-66f9b9ff2ffa",
            "brand": "Brown-Joseph",
            "tasks_completed": [
                {
                    "task_id": "2b244358-1497-4084-8fee-8188527cba15",
                    "platform": "TikTok",
                    "post_url": "https://www.bowers.com/",
                    "likes": 4754,
                    "comments": 1,
                    "shares": 29,
                    "reach": 7573
                }
            ],
            "total_sales_attributed": 3290.0
        }
    ]
}