{
    "user_id": "346af6ca-95cd-4f1d-a35e-f73262ba47c8",
    "name": "Carol Love",
    "email": "perezjose@example.com",
    "instagram_handle": "@richard94",
    "tiktok_handle": "@kelly15",
    "joined_at": "2025-01-10T00:48:36.316064",
    "advocacy_programs": [
        {
            "program_id": "1ae61294-2025-48a9-b14b-d13d41cd1e30",
            "brand": "Flynn-Burns",
            "tasks_completed": [
                {
                    "task_id": "17e4ea31-fe2a-4c62-9b49-0d08e862fc7a",
                    "platform": "Instagram",
                    "post_url": "http://pollard-klein.com/",
                    "likes": 4656,
                    "comments": 44,
                    "shares": 63,
                    "reach": 6917
                }
            ],
            "total_sales_attributed": 2510.52
        }
    ]
}