{
    "user_id": "75c9beb1-cb0d-4176-bfbc-e6f54f78e9a9",
    "name": "William Scott",
    "email": "lacosta@example.com",
    "instagram_handle": "@johnsonbrian",
    "tiktok_handle": "@janetgrant",
    "joined_at": "2024-06-13T15:24:26.037001",
    "advocacy_programs": [
        {
            "program_id": "98e4548b-b72b-4680-9e50-36fd391f6555",
            "brand": "Conrad-Cruz",
            "tasks_completed": [
                {
                    "task_id": "4502d060-4fe9-47df-a4eb-f9c6d1747ee8",
                    "platform": "Facebook",
                    "post_url": "http://www.rodriguez.net/",
                    "likes": 5405,
                    "comments": 95,
                    "shares": 0,
                    "reach": 6370
                }
            ],
            "total_sales_attributed": 4503.854271006523
        }
    ]
}