{
    "user_id": "a041eb4b-1811-4c92-8a7a-3b42220f1c71",
    "name": "Jessica Dean",
    "email": "woodseric@example.net",
    "instagram_handle": "@jessicadixon",
    "tiktok_handle": "@elizabeth75",
    "joined_at": "2025-02-25T02:32:18.826766",
    "advocacy_programs": [
        {
            "program_id": "e8a0b73b-7d5a-4a62-96b2-eb7592929ac3",
            "brand": "Andrade, Cook and Horn",
            "tasks_completed": [
                {
                    "task_id": "0a36f210-16fa-4016-9311-1785bb9e2d0c",
                    "platform": "TikTok",
                    "post_url": "https://www.rodriguez.com/",
                    "likes": 9742,
                    "comments": 500,
                    "shares": 96,
                    "reach": 4652
                }
            ],
            "total_sales_attributed": 8666.87
        }
    ]
}