{
    "user_id": "76b3252e-e44e-473b-b964-e8b2204f6cba",
    "name": "Connie Duncan",
    "email": "moorepaula@example.net",
    "instagram_handle": "@derrick19",
    "tiktok_handle": "@alicia48",
    "joined_at": "2023-10-15T13:08:08.298709",
    "advocacy_programs": [
        {
            "program_id": "a82bad55-c8f7-4321-82b0-2f56f360c5d3",
            "brand": "Lopez, Lewis and Williams",
            "tasks_completed": [
                {
                    "task_id": "de3f5078-6c04-4176-84e3-64e7a0be492b",
                    "platform": "Instagram",
                    "post_url": "https://metallic-underpants.org/",
                    "likes": 2791,
                    "comments": 152,
                    "shares": 71,
                    "reach": 5557
                }
            ],
            "total_sales_attributed": 4108.088221196379
        }
    ]
}