{
    "user_id": "af2b8cd8-523e-40ee-8895-ac98710aaa01",
    "name": "Tiffany Miller",
    "email": "Cooper_Larson@hotmail.com",
    "instagram_handle": "@jmartinez",
    "tiktok_handle": "@harringtonjohn",
    "joined_at": "2024-07-11T20:29:38.828159",
    "advocacy_programs": [
        {
            "program_id": "1fde20a7-ce74-432e-95ee-40b479b956a2",
            "brand": "Dodson-Morales",
            "tasks_completed": [
                {
                    "task_id": "bc02d2ec-4539-42cd-a9cc-f5b5dae1c8b0",
                    "platform": "Instagram",
                    "post_url": "http://smith.com/",
                    "likes": 2941,
                    "comments": 186,
                    "shares": 23,
                    "reach": 1124
                }
            ],
            "total_sales_attributed": 7827.33
        }
    ]
}