{
    "user_id": "7c57883d-c521-4085-aca0-d9aec784aa43",
    "name": "Alicia Wang",
    "email": "lauren36@example.com",
    "instagram_handle": "@usmith",
    "tiktok_handle": "@xknapp",
    "joined_at": "2023-10-01T03:47:33.352359",
    "advocacy_programs": [
        {
            "program_id": "2c51f4ac-f67a-46fe-aa0b-18265a0c8dd4",
            "brand": "Fisher-Fields",
            "tasks_completed": [
                {
                    "task_id": "f6aa191a-bdb6-44ca-8643-498c717fce20",
                    "platform": "Instagram",
                    "post_url": "http://parker.org/",
                    "likes": 2912,
                    "comments": 230,
                    "shares": 34,
                    "reach": 2324
                }
            ],
            "total_sales_attributed": 1695.42
        }
    ]
}