{
    "user_id": "efcdf26b-6227-416c-9a04-2e623609ad4c",
    "name": "Erika Smith",
    "email": "lambertcatherine@example.com",
    "instagram_handle": "@catherinedunn",
    "tiktok_handle": "@james71",
    "joined_at": "2024-06-30T11:44:51.537559",
    "advocacy_programs": [
        {
            "program_id": "0a03627c-ac23-43e3-89d6-627ced78b8e4",
            "brand": "Rhodes-Gilbert",
            "tasks_completed": [
                {
                    "task_id": "aa0eccac-a4e1-49fc-ab91-0175f108ab92",
                    "platform": "TikTok",
                    "post_url": "http://www.coleman-lee.com/",
                    "likes": 203,
                    "comments": 9,
                    "shares": 65,
                    "reach": -1000
                }
            ],
            "total_sales_attributed": 2693.19
        }
    ]
}