{
    "user_id": "3560af44-5fe6-44b1-a6b6-2348004ebc7f",
    "name": "Deborah Owen",
    "email": "daniellestewart@example.net",
    "instagram_handle": "@Madilyn_Medhurst",
    "tiktok_handle": "@saunderskayla",
    "joined_at": "2023-11-03T17:57:39.636760",
    "advocacy_programs": [
        {
            "program_id": "7d2924ba-be8b-4a88-940c-2462e46f90e8",
            "brand": "Cantu, Simpson and Oliver",
            "tasks_completed": [
                {
                    "task_id": "4fda313f-5087-467d-852a-1b9a6f873913",
                    "platform": "YouTube",
                    "post_url": "http://clay.com/",
                    "likes": 1861,
                    "comments": 157,
                    "shares": 13,
                    "reach": 4273
                }
            ],
            "total_sales_attributed": 9502.02
        }
    ]
}