{
    "user_id": "fd758315-138f-4914-9e8b-14630174aafe",
    "name": "Ronnie Park",
    "email": "pwilliamson@example.net",
    "instagram_handle": "@richmondkristy",
    "tiktok_handle": "@christophermoreno",
    "joined_at": "2024-06-13T05:28:31.970Z",
    "advocacy_programs": [
        {
            "program_id": "a66cd62c-d731-4a64-bc06-7fc8233ecec3",
            "brand": "Rempel, Ferry and Swaniawski",
            "tasks_completed": [
                {
                    "task_id": "de2b4838-4c1b-44b3-a909-c7d2f5cfd728",
                    "platform": "Instagram",
                    "post_url": "https://sorrowful-marathon.name",
                    "likes": 6762,
                    "comments": 232,
                    "shares": 46,
                    "reach": 4506
                }
            ],
            "total_sales_attributed": 5554.41
        }
    ]
}