{
    "user_id": "cad8b57f-edc8-4837-bf61-64c0fb5878cf",
    "name": "Tiffany Owen",
    "email": "hallgina@example.org",
    "instagram_handle": "@marshdylan",
    "tiktok_handle": "@hillamy",
    "joined_at": "2024-07-09T17:42:52.866Z",
    "advocacy_programs": [
        {
            "program_id": "6aa6c9fd-1210-457f-8e41-cb1333ebc8db",
            "brand": "Spinka Group",
            "tasks_completed": [
                {
                    "task_id": "7aabd0ce-9332-4efa-9075-0f08ee95b37f",
                    "platform": "Instagram",
                    "post_url": "http://www.klein.com/",
                    "likes": 2157,
                    "comments": 267,
                    "shares": 50,
                    "reach": 2312
                }
            ],
            "total_sales_attributed": 5139.69
        }
    ]
}