{
    "user_id": "dcbe1191-273c-4345-bf72-ca22b519c414",
    "name": "Joseph Velez",
    "email": "belljeffery@example.org",
    "instagram_handle": "@mark86",
    "tiktok_handle": "@glopez",
    "joined_at": "2024-06-24T20:21:19.148324",
    "advocacy_programs": [
        {
            "program_id": "af8b5ddd-05c0-47b3-b4ad-8bb82b34f8dd",
            "brand": "Wood, Hall and Cowan",
            "tasks_completed": [
                {
                    "task_id": "412fe62e-0e38-4f2f-bdf0-7acabe091751",
                    "platform": "Instagram",
                    "post_url": "https://scott-ross.org/",
                    "likes": 6123,
                    "comments": 23,
                    "shares": 18,
                    "reach": 4589
                }
            ],
            "total_sales_attributed": 5405.78
        }
    ]
}