{
    "user_id": "9c59b7b3-a35b-4154-bb41-efc35c7de68d",
    "name": "William Fisher",
    "email": "Melvin17@yahoo.com",
    "instagram_handle": "@david10",
    "tiktok_handle": "@elliottmike",
    "joined_at": "2025-04-30T11:39:38.521283",
    "advocacy_programs": [
        {
            "program_id": "7ef564ec-6f5d-4dd3-8e9a-471e9c1c579e",
            "brand": "Barron, Horton and Barber",
            "tasks_completed": [
                {
                    "task_id": "5777850f-4c1e-4b57-a6a0-c4519e027538",
                    "platform": "TikTok",
                    "post_url": "https://yoder.com/",
                    "likes": 5264,
                    "comments": 93,
                    "shares": 1,
                    "reach": 4015
                }
            ],
            "total_sales_attributed": 106.8521679626112
        }
    ]
}