{
    "user_id": "0f074aab-be23-4419-a8e5-3203b9dbf2ed",
    "name": "Joseph Armstrong",
    "email": "johnwarren@example.com",
    "instagram_handle": "@angie95",
    "tiktok_handle": "@harrisonheather",
    "joined_at": "2024-08-08T10:59:29.058064",
    "advocacy_programs": [
        {
            "program_id": "20ed08b7-4507-4b3a-a395-652762c01e7a",
            "brand": "Fisher PLC",
            "tasks_completed": [
                {
                    "task_id": "1bdb6fa4-0fd7-4c6a-ae51-0d4493855a8b",
                    "platform": "Twitter",
                    "post_url": "https://collins.com/",
                    "likes": 352,
                    "comments": 315,
                    "shares": 8,
                    "reach": 5748
                }
            ],
            "total_sales_attributed": 4681.38
        }
    ]
}