{
    "user_id": "fa81158e-27bc-435c-9930-4c77e2a0f672",
    "name": "Justin Walls",
    "email": "mcneildavid@example.org",
    "instagram_handle": "@kimclayton",
    "tiktok_handle": "@jroberts",
    "joined_at": "2024-08-05T12:26:59.704Z",
    "advocacy_programs": [
        {
            "program_id": "aa3eda68-7b3f-4786-9b06-9222b6b2d12d",
            "brand": "Townsend Group",
            "tasks_completed": [
                {
                    "task_id": "660b72ee-2db6-49fc-aac5-e215e23a4d84",
                    "platform": "TikTok",
                    "post_url": "http://velasquez.com/",
                    "likes": 4994,
                    "comments": 422,
                    "shares": 8,
                    "reach": 1851
                }
            ],
            "total_sales_attributed": 4805.850580063116
        }
    ]
}